MANIFEST.in
README.txt
setup.cfg
setup.py
docs/HISTORY.txt
pcommerce/__init__.py
pcommerce.payment.saferpay.egg-info/PKG-INFO
pcommerce.payment.saferpay.egg-info/SOURCES.txt
pcommerce.payment.saferpay.egg-info/dependency_links.txt
pcommerce.payment.saferpay.egg-info/entry_points.txt
pcommerce.payment.saferpay.egg-info/namespace_packages.txt
pcommerce.payment.saferpay.egg-info/not-zip-safe
pcommerce.payment.saferpay.egg-info/requires.txt
pcommerce.payment.saferpay.egg-info/top_level.txt
pcommerce/payment/__init__.py
pcommerce/payment/saferpay/__init__.py
pcommerce/payment/saferpay/config.py
pcommerce/payment/saferpay/configure.zcml
pcommerce/payment/saferpay/data.py
pcommerce/payment/saferpay/interfaces.py
pcommerce/payment/saferpay/plugin.py
pcommerce/payment/saferpay/setuphandlers.py
pcommerce/payment/saferpay/browser/__init__.py
pcommerce/payment/saferpay/browser/configlet.pt
pcommerce/payment/saferpay/browser/configlet.py
pcommerce/payment/saferpay/browser/configure.zcml
pcommerce/payment/saferpay/browser/confirmation.pt
pcommerce/payment/saferpay/browser/confirmation.py
pcommerce/payment/saferpay/browser/icon.gif
pcommerce/payment/saferpay/browser/logo.gif
pcommerce/payment/saferpay/browser/overview.pt
pcommerce/payment/saferpay/browser/overview.py
pcommerce/payment/saferpay/browser/payment.py
pcommerce/payment/saferpay/browser/process.py
pcommerce/payment/saferpay/i18n/pcommerce-de.mo
pcommerce/payment/saferpay/i18n/pcommerce-de.po
pcommerce/payment/saferpay/i18n/pcommerce-nl.mo
pcommerce/payment/saferpay/i18n/pcommerce-nl.po
pcommerce/payment/saferpay/i18n/pcommerce.pot
pcommerce/payment/saferpay/profiles/default/controlpanel.xml
pcommerce/payment/saferpay/profiles/default/metadata.xml
pcommerce/payment/saferpay/profiles/default/pcommerce.payment.saferpay_various.txt