Metadata-Version: 1.0
Name: pcommerce.payment.saferpay
Version: 1.0b4
Summary: A SaferPay payment method for PCommerce
Home-page: http://raptus.com
Author: Raptus AG
Author-email: dev@raptus.com
License: GPL
Platform: UNKNOWN
Classifier: Programming Language :: Python
Classifier: Topic :: Software Development :: Libraries :: Python Modules
